{
  "generated_at": "2026-06-10T05:00:10.220Z",
  "events": [
    {
      "type": "breadth_up",
      "ticker": "BREADTH",
      "name": "Pelebaran kenaikan pasar",
      "change_pct": 78.4,
      "label": "75% saham menguat",
      "drivers": {
        "sectors": [
          {
            "avg_change_pct": 0
          },
          {
            "avg_change_pct": 0
          },
          {
            "avg_change_pct": 0
          }
        ],
        "tickers": [
          {
            "ticker": "BNBR",
            "change_pct": 28.24,
            "contribution_score": 568.87
          },
          {
            "ticker": "BTEK",
            "change_pct": 22.22,
            "contribution_score": 362.41
          },
          {
            "ticker": "DSSA",
            "change_pct": 17.04,
            "contribution_score": 329.54
          }
        ],
        "foreign_flow": null,
        "macro_active": null
      },
      "detected_at": "2026-06-10T05:00:10.220Z",
      "status": "active",
      "summary": null
    },
    {
      "type": "breadth_up",
      "ticker": "BREADTH",
      "name": "Pelebaran kenaikan pasar",
      "change_pct": 80,
      "label": "71% saham menguat",
      "drivers": {
        "sectors": [
          {
            "avg_change_pct": 0
          },
          {
            "avg_change_pct": 0
          },
          {
            "avg_change_pct": 0
          }
        ],
        "tickers": [
          {
            "ticker": "BTEK",
            "change_pct": 22.22,
            "contribution_score": 354.05
          },
          {
            "ticker": "DSSA",
            "change_pct": 15.56,
            "contribution_score": 295.25
          },
          {
            "ticker": "TRON",
            "change_pct": 18.31,
            "contribution_score": 259.32
          }
        ],
        "foreign_flow": null,
        "macro_active": null
      },
      "detected_at": "2026-06-10T03:30:10.061Z",
      "status": "active",
      "summary": null
    },
    {
      "type": "breadth_up",
      "ticker": "BREADTH",
      "name": "Pelebaran kenaikan pasar",
      "change_pct": 100,
      "label": "100% saham menguat",
      "drivers": {
        "sectors": [
          {
            "avg_change_pct": 0
          },
          {
            "avg_change_pct": 0
          },
          {
            "avg_change_pct": 0
          }
        ],
        "tickers": [
          {
            "ticker": "FASW",
            "change_pct": 2.59,
            "contribution_score": 5.57
          }
        ],
        "foreign_flow": null,
        "macro_active": null
      },
      "detected_at": "2026-06-10T02:00:10.413Z",
      "status": "active",
      "summary": null
    },
    {
      "type": "rapid_down",
      "ticker": "WIRG",
      "name": "WIRG",
      "change_pct": 1.92,
      "move_30min": -3.64,
      "label": "WIRG -3.6% dalam 30 menit",
      "drivers": {
        "sectors": [
          {
            "avg_change_pct": 0
          },
          {
            "avg_change_pct": 0
          },
          {
            "avg_change_pct": 0
          }
        ],
        "tickers": [
          {
            "ticker": "BNBR",
            "change_pct": 28.24,
            "contribution_score": 568.87
          },
          {
            "ticker": "BTEK",
            "change_pct": 22.22,
            "contribution_score": 362.41
          },
          {
            "ticker": "DSSA",
            "change_pct": 17.04,
            "contribution_score": 329.54
          }
        ],
        "foreign_flow": null,
        "macro_active": null
      },
      "detected_at": "2026-06-10T05:00:10.220Z",
      "status": "active",
      "summary": null
    },
    {
      "type": "rapid_down",
      "ticker": "ARII",
      "name": "PT Atlas Resources Tbk",
      "change_pct": 6.15,
      "move_30min": -4.83,
      "label": "ARII -4.8% dalam 30 menit",
      "drivers": {
        "sectors": [
          {
            "avg_change_pct": 0
          },
          {
            "avg_change_pct": 0
          },
          {
            "avg_change_pct": 0
          }
        ],
        "tickers": [
          {
            "ticker": "BNBR",
            "change_pct": 28.24,
            "contribution_score": 568.87
          },
          {
            "ticker": "BTEK",
            "change_pct": 22.22,
            "contribution_score": 362.41
          },
          {
            "ticker": "DSSA",
            "change_pct": 17.04,
            "contribution_score": 329.54
          }
        ],
        "foreign_flow": null,
        "macro_active": null
      },
      "detected_at": "2026-06-10T05:00:10.220Z",
      "status": "active",
      "summary": null
    }
  ]
}